pyshade/__init__.py
pyshade-0.0.8.dist-info/METADATA
pyshade-0.0.8.dist-info/WHEEL
pyshade-0.0.8.dist-info/top_level.txt
pyshade-0.0.8.dist-info/RECORD
