Metadata-Version: 2.1
Name: pyshade
Version: 0.0.8
Summary: a python module that will allow you to make a colorful text with dynamics colors and display your text slowly
Keywords: python,sockets
